odoo/addons/attachment_db_by_checksum/README.rst
odoo/addons/attachment_db_by_checksum/__init__.py
odoo/addons/attachment_db_by_checksum/__manifest__.py
odoo/addons/attachment_db_by_checksum/i18n/attachment_db_by_checksum.pot
odoo/addons/attachment_db_by_checksum/i18n/it.po
odoo/addons/attachment_db_by_checksum/models/__init__.py
odoo/addons/attachment_db_by_checksum/models/ir_attachment.py
odoo/addons/attachment_db_by_checksum/models/ir_attachment_content.py
odoo/addons/attachment_db_by_checksum/readme/CONFIGURE.rst
odoo/addons/attachment_db_by_checksum/readme/CONTRIBUTORS.rst
odoo/addons/attachment_db_by_checksum/readme/DESCRIPTION.rst
odoo/addons/attachment_db_by_checksum/security/ir.model.access.csv
odoo/addons/attachment_db_by_checksum/static/description/icon.png
odoo/addons/attachment_db_by_checksum/static/description/index.html
odoo/addons/attachment_db_by_checksum/tests/__init__.py
odoo/addons/attachment_db_by_checksum/tests/test_attachment_by_checksum.py
odoo14_addon_attachment_db_by_checksum-14.0.1.0.1.dev4.dist-info/METADATA
odoo14_addon_attachment_db_by_checksum-14.0.1.0.1.dev4.dist-info/WHEEL
odoo14_addon_attachment_db_by_checksum-14.0.1.0.1.dev4.dist-info/top_level.txt
odoo14_addon_attachment_db_by_checksum-14.0.1.0.1.dev4.dist-info/RECORD
