Metadata-Version: 2.1
Name: odoo14-addon-attachment_db_by_checksum
Version: 14.0.1.0.1.dev4
Summary: Allow to identify database attachments through their hash, avoiding duplicates
Home-page: https://github.com/OCA/storage
Author: TAKOBI, Odoo Community Association (OCA)
Author-email: support@odoo-community.org
License: LGPL-3
Classifier: Programming Language :: Python
Classifier: Framework :: Odoo
Classifier: Framework :: Odoo :: 14.0
Classifier: License :: OSI Approved :: GNU Lesser General Public License v3 (LGPLv3)
Requires-Python: >=3.6
Requires-Dist: odoo<14.1dev,>=14.0a
